{
  "audit_date": "2024-01-06",
  "component_analysis": {
    "existing_components": {
      "ProductCard.js": {
        "location": "components/ProductCard.js",
        "status": "unused",
        "description": "Basic product card component not used in current implementation",
        "issues": [
          "Not integrated with current products page",
          "Missing modern styling",
          "No TypeScript support"
        ]
      },
      "ConfiguratorWizard.tsx": {
        "location": "components/configurator/ConfiguratorWizard.tsx",
        "status": "working",
        "description": "4-step product configuration wizard",
        "features": [
          "Product specifications",
          "Design options",
          "Review and confirm",
          "Pricing integration"
        ]
      },
      "DeliveryDateBadge.tsx": {
        "location": "components/shipping/DeliveryDateBadge.tsx",
        "status": "working",
        "description": "Displays estimated delivery dates on products",
        "features": [
          "ETA calculation",
          "ZIP code integration",
          "Analytics tracking"
        ]
      },
      "CutoffCountdown.tsx": {
        "location": "components/shipping/CutoffCountdown.tsx",
        "status": "working",
        "description": "Shows countdown to daily production cutoff",
        "features": [
          "Real-time countdown",
          "Business day calculation",
          "Analytics tracking"
        ]
      }
    },
    "missing_components": {
      "ProductCard.tsx": {
        "priority": "high",
        "description": "Modern product card for catalog grid",
        "requirements": [
          "Image display with fallback",
          "Product name and description",
          "Price display",
          "CTA buttons",
          "Hover effects",
          "Accessibility compliance"
        ]
      },
      "ProductGrid.tsx": {
        "priority": "high",
        "description": "Responsive grid layout for products",
        "requirements": [
          "Responsive grid (1/2/3/4 columns)",
          "Loading skeletons",
          "Empty state handling",
          "Filter integration"
        ]
      },
      "ProductHero.tsx": {
        "priority": "medium",
        "description": "Hero section for product detail pages",
        "requirements": [
          "Large product image",
          "Product title and description",
          "Primary CTA button",
          "Breadcrumb navigation"
        ]
      },
      "ProductSpecs.tsx": {
        "priority": "medium",
        "description": "Product specifications display",
        "requirements": [
          "Specifications list",
          "Features list",
          "Technical details",
          "Material information"
        ]
      },
      "ProductGallery.tsx": {
        "priority": "low",
        "description": "Image gallery for product detail pages",
        "requirements": [
          "Multiple image display",
          "Thumbnail navigation",
          "Zoom functionality",
          "Mobile optimization"
        ]
      }
    },
    "integration_points": {
      "analytics": {
        "components": [
          "ProductCard.tsx",
          "ProductGrid.tsx",
          "ProductHero.tsx"
        ],
        "events": [
          "product_viewed",
          "product_clicked",
          "configurator_opened"
        ]
      },
      "shipping": {
        "components": [
          "ProductCard.tsx",
          "ProductHero.tsx"
        ],
        "features": [
          "Delivery date display",
          "Cutoff countdown",
          "Shipping options"
        ]
      },
      "pricing": {
        "components": [
          "ProductCard.tsx",
          "ProductSpecs.tsx",
          "ConfiguratorWizard.tsx"
        ],
        "features": [
          "Starting price display",
          "Dynamic pricing",
          "Quote generation"
        ]
      }
    },
    "styling_requirements": {
      "design_system": {
        "colors": {
          "primary": "blue-600",
          "secondary": "gray-600",
          "accent": "yellow-400",
          "success": "green-600"
        },
        "spacing": {
          "card_padding": "p-6",
          "grid_gap": "gap-6",
          "section_padding": "py-12"
        },
        "shadows": {
          "card": "shadow-lg",
          "hover": "shadow-xl",
          "button": "shadow-md"
        }
      },
      "responsive_breakpoints": {
        "mobile": "grid-cols-1",
        "tablet": "sm:grid-cols-2",
        "desktop": "lg:grid-cols-3",
        "large": "xl:grid-cols-4"
      }
    }
  },
  "implementation_plan": {
    "phase_1": {
      "priority": "critical",
      "components": [
        "ProductCard.tsx",
        "ProductGrid.tsx"
      ],
      "timeline": "1-2 days",
      "dependencies": [
        "Unified product catalog",
        "Image placeholder system"
      ]
    },
    "phase_2": {
      "priority": "high",
      "components": [
        "ProductHero.tsx",
        "ProductSpecs.tsx"
      ],
      "timeline": "2-3 days",
      "dependencies": [
        "Product detail page structure",
        "Static generation setup"
      ]
    },
    "phase_3": {
      "priority": "medium",
      "components": [
        "ProductGallery.tsx"
      ],
      "timeline": "3-5 days",
      "dependencies": [
        "Multiple product images",
        "Image optimization system"
      ]
    }
  },
  "testing_requirements": {
    "unit_tests": [
      "ProductCard rendering",
      "ProductGrid layout",
      "Image fallback handling",
      "CTA button functionality"
    ],
    "integration_tests": [
      "Product page navigation",
      "Configurator integration",
      "Analytics event firing",
      "Shipping component integration"
    ],
    "accessibility_tests": [
      "Keyboard navigation",
      "Screen reader compatibility",
      "Color contrast compliance",
      "Focus management"
    ]
  }
}
